puzzlecreator/__init__.py
puzzlecreator/crossword.py
puzzlecreator-1.1.4.dist-info/LICENSE
puzzlecreator-1.1.4.dist-info/METADATA
puzzlecreator-1.1.4.dist-info/WHEEL
puzzlecreator-1.1.4.dist-info/top_level.txt
puzzlecreator-1.1.4.dist-info/RECORD
