Metadata-Version: 2.1
Name: puzzlecreator
Version: 1.1.4
Summary: A package for creating crossword puzzles by Orchid Box.
Home-page: https://orchidbox.com/
Author: frank vitetta
Author-email: frank@orchidbox.com
Classifier: Programming Language :: Python :: 3
Classifier: License :: OSI Approved :: MIT License
Classifier: Operating System :: OS Independent
Requires-Python: >=3.6
License-File: LICENSE
